aioytt/__init__.py
aioytt/caption.py
aioytt/errors.py
aioytt/py.typed
aioytt/transcript.py
aioytt/video_id.py
aioytt-0.2.5.dist-info/METADATA
aioytt-0.2.5.dist-info/WHEEL
aioytt-0.2.5.dist-info/licenses/LICENSE
aioytt-0.2.5.dist-info/RECORD
